_libvips.abi3.so
pyvips_binary-8.18.0.dist-info/RECORD
pyvips_binary-8.18.0.dist-info/WHEEL
pyvips_binary-8.18.0.dist-info/top_level.txt
pyvips_binary-8.18.0.dist-info/METADATA
pyvips_binary-8.18.0.dist-info/licenses/LICENSE
pyvips_binary.dylibs/libvips.42.dylib
