Metadata-Version: 2.4
Name: pyvips-binary
Version: 8.18.0
Summary: Binary distribution of libvips and dependencies for use with pyvips
Author-email: Kleis Auke Wolthuizen <info@kleisauke.nl>
License: LGPL-3.0-or-later
Project-URL: changelog, https://github.com/kleisauke/pyvips-binary/blob/main/CHANGELOG.md
Project-URL: funding, https://opencollective.com/libvips
Project-URL: homepage, https://github.com/kleisauke/pyvips-binary
Project-URL: issues, https://github.com/kleisauke/pyvips-binary/issues
Project-URL: source, https://github.com/kleisauke/pyvips-binary
Classifier: Development Status :: 5 - Production/Stable
Classifier: Environment :: Console
Classifier: Intended Audience :: Developers
Classifier: Intended Audience :: Science/Research
Classifier: Topic :: Multimedia :: Graphics
Classifier: Topic :: Multimedia :: Graphics :: Graphics Conversion
Classifier: License :: OSI Approved :: GNU Lesser General Public License v3 or later (LGPLv3+)
Classifier: Programming Language :: Python
Classifier: Programming Language :: Python :: 3
Classifier: Programming Language :: Python :: 3 :: Only
Classifier: Programming Language :: Python :: 3.7
Classifier: Programming Language :: Python :: 3.8
Classifier: Programming Language :: Python :: 3.9
Classifier: Programming Language :: Python :: 3.10
Classifier: Programming Language :: Python :: 3.11
Classifier: Programming Language :: Python :: 3.12
Classifier: Programming Language :: Python :: 3.13
Classifier: Programming Language :: Python :: 3.14
Classifier: Programming Language :: Python :: Implementation :: CPython
Requires-Python: >=3.7
License-File: LICENSE
Requires-Dist: cffi>=1.0.0
Dynamic: license-file
